django_request_mapping/__init__.py
django_request_mapping/decorator.py
django_request_mapping/route.py
django_request_mapping-0.0.12.dist-info/LICENSE
django_request_mapping-0.0.12.dist-info/METADATA
django_request_mapping-0.0.12.dist-info/WHEEL
django_request_mapping-0.0.12.dist-info/top_level.txt
django_request_mapping-0.0.12.dist-info/RECORD
