Metadata-Version: 2.1
Name: django-request-mapping
Version: 0.0.12
Summary: spring-like request_mapping for django.
Home-page: https://github.com/sazima/django-request-mapping
Author: wukt
Author-email: w@wktadmin.com
License: UNKNOWN
Platform: UNKNOWN
Classifier: Programming Language :: Python :: 3
Classifier: License :: OSI Approved :: MIT License
Classifier: Operating System :: OS Independent
